wols/__init__.py
wols/constants.py
wols/exceptions.py
wols/logo.png
wols/py.typed
wols/cli/__init__.py
wols/cli/app.py
wols/core/__init__.py
wols/core/create.py
wols/core/parse.py
wols/core/serialize.py
wols/core/validate.py
wols/crypto/__init__.py
wols/crypto/decrypt.py
wols/crypto/encrypt.py
wols/models/__init__.py
wols/models/enums.py
wols/models/specimen.py
wols/models/validation.py
wols/qr/__init__.py
wols/qr/generate.py
wols/qr/scan.py
wols-0.1.1.dist-info/METADATA
wols-0.1.1.dist-info/WHEEL
wols-0.1.1.dist-info/entry_points.txt
wols-0.1.1.dist-info/licenses/LICENSE
wols-0.1.1.dist-info/RECORD
