Metadata-Version: 2.4
Name: wols
Version: 0.1.1
Summary: WeMush Open Labeling Standard (WOLS) Python library
Project-URL: Homepage, https://github.com/wemush/specimen-labels-py
Project-URL: Documentation, https://wemush.github.io/specimen-labels-py
Project-URL: Repository, https://github.com/wemush/specimen-labels-py
Project-URL: Issues, https://github.com/wemush/specimen-labels-py/issues
Author-email: WeMush <dev@wemush.com>
License-Expression: Apache-2.0
License-File: LICENSE
Keywords: cli,cultivation,label,mushroom,qr,specimen,wols
Classifier: Development Status :: 4 - Beta
Classifier: Intended Audience :: Developers
Classifier: License :: OSI Approved :: Apache Software License
Classifier: Programming Language :: Python :: 3
Classifier: Programming Language :: Python :: 3.12
Classifier: Programming Language :: Python :: 3.13
Classifier: Programming Language :: Python :: 3.14
Classifier: Topic :: Scientific/Engineering
Classifier: Typing :: Typed
Requires-Python: >=3.12
Requires-Dist: cuid2>=2.0
Provides-Extra: all
Requires-Dist: cryptography>=42.0; extra == 'all'
Requires-Dist: pillow>=10.0; extra == 'all'
Requires-Dist: pyzbar>=0.1.9; extra == 'all'
Requires-Dist: qrcode[pil]>=7.4; extra == 'all'
Requires-Dist: rich>=13.0; extra == 'all'
Requires-Dist: typer>=0.12; extra == 'all'
Provides-Extra: cli
Requires-Dist: rich>=13.0; extra == 'cli'
Requires-Dist: typer>=0.12; extra == 'cli'
Provides-Extra: crypto
Requires-Dist: cryptography>=42.0; extra == 'crypto'
Provides-Extra: dev
Requires-Dist: mypy>=1.8; extra == 'dev'
Requires-Dist: pytest-cov>=4.0; extra == 'dev'
Requires-Dist: pytest>=8.0; extra == 'dev'
Requires-Dist: ruff>=0.4; extra == 'dev'
Requires-Dist: twine>=5.0; extra == 'dev'
Provides-Extra: qr
Requires-Dist: pillow>=10.0; extra == 'qr'
Requires-Dist: pyzbar>=0.1.9; extra == 'qr'
Requires-Dist: qrcode[pil]>=7.4; extra == 'qr'
